shorttext_bert/__init__.py
shorttext_bert/bertobj.py
shorttext_bert/encoder.py
shorttext_bert/scorer.py
shorttext_bert-0.0.1.dist-info/licenses/LICENSE
shorttext_bert-0.0.1.dist-info/METADATA
shorttext_bert-0.0.1.dist-info/WHEEL
shorttext_bert-0.0.1.dist-info/top_level.txt
shorttext_bert-0.0.1.dist-info/RECORD
